lucena/__init__.py
lucena/client.py
lucena/exceptions.py
lucena/message_handler.py
lucena/service.py
lucena/worker.py
lucena-0.6.1.dist-info/DESCRIPTION.rst
lucena-0.6.1.dist-info/METADATA
lucena-0.6.1.dist-info/RECORD
lucena-0.6.1.dist-info/WHEEL
lucena-0.6.1.dist-info/metadata.json
lucena-0.6.1.dist-info/top_level.txt
