Metadata-Version: 2.0
Name: lucena
Version: 0.6.1
Summary: Python core library for building web services in Lucena Project.
Home-page: https://github.com/lucenaproject
Author: Fernando Miranda
Author-email: fcmiranda@gmail.com
License: MIT
Platform: UNKNOWN
Classifier: Development Status :: 2 - Pre-Alpha
Classifier: Intended Audience :: Developers
Classifier: Topic :: Software Development :: Build Tools
Classifier: Topic :: Software Development :: Object Brokering
Classifier: License :: OSI Approved :: MIT License
Requires-Python: >=3.6
Requires-Dist: pyzmq
